{
  "data": [
    {
      "id": 1901,
      "songNumber": "94535712",
      "rank": 1,
      "title": "사랑은 늘 도망가",
      "albumArt": "https://image.genie.co.kr/Y/IMAGE/IMG_ALBUM/082/322/594/82322594_1633671778123_1_140x140.JPG/dims/resize/Q_80,0",
      "albumName": "신사와 아가씨 OST Part.2",
      "artistName": "임영웅",
      "date": "2022-12-06",
      "bf_day": -7,
      "bf_week": null,
      "bf_month": null,
      "platform": "genie"
    },
    {
      "id": 1902,
      "songNumber": "96549502",
      "rank": 2,
      "title": "우리들의 블루스",
      "albumArt": "https://image.genie.co.kr/Y/IMAGE/IMG_ALBUM/082/638/032/82638032_1651479062721_1_140x140.JPG/dims/resize/Q_80,0",
      "albumName": "IM HERO",
      "artistName": "임영웅",
      "date": "2022-12-06",
      "bf_day": -8,
      "bf_week": null,
      "bf_month": null,
      "platform": "genie"
    },
    {
      "id": 1903,
      "songNumber": "99014221",
      "rank": 3,
      "title": "London Boy",
      "albumArt": "https://image.genie.co.kr/Y/IMAGE/IMG_ALBUM/083/180/213/83180213_1668490985544_1_140x140.JPG/dims/resize/Q_80,0",
      "albumName": "Polaroid",
      "artistName": "임영웅",
      "date": "2022-12-06",
      "bf_day": -13,
      "bf_week": null,
      "bf_month": null,
      "platform": "genie"
    },
    {
      "id": 1904,
      "songNumber": "96696809",
      "rank": 4,
      "title": "다시 만날 수 있을까",
      "albumArt": "https://image.genie.co.kr/Y/IMAGE/IMG_ALBUM/082/638/032/82638032_1651479062721_1_140x140.JPG/dims/resize/Q_80,0",
      "albumName": "IM HERO",
      "artistName": "임영웅",
      "date": "2022-12-06",
      "bf_day": -8,
      "bf_week": null,
      "bf_month": null,
      "platform": "genie"
    },
    {
      "id": 1905,
      "songNumber": "99014222",
      "rank": 5,
      "title": "Polaroid",
      "albumArt": "https://image.genie.co.kr/Y/IMAGE/IMG_ALBUM/083/180/213/83180213_1668490985544_1_140x140.JPG/dims/resize/Q_80,0",
      "albumName": "Polaroid",
      "artistName": "임영웅",
      "date": "2022-12-06",
      "bf_day": -13,
      "bf_week": null,
      "bf_month": null,
      "platform": "genie"
    },
    {
      "id": 1906,
      "songNumber": "90077755",
      "rank": 6,
      "title": "이제 나만 믿어요",
      "albumArt": "https://image.genie.co.kr/Y/IMAGE/IMG_ALBUM/081/410/156/81410156_1585878705990_1_140x140.JPG/dims/resize/Q_80,0",
      "albumName": "내일은 미스터트롯 우승자 특전곡",
      "artistName": "임영웅",
      "date": "2022-12-06",
      "bf_day": -8,
      "bf_week": null,
      "bf_month": null,
      "platform": "genie"
    },
    {
      "id": 1907,
      "songNumber": "96696807",
      "rank": 7,
      "title": "무지개",
      "albumArt": "https://image.genie.co.kr/Y/IMAGE/IMG_ALBUM/082/638/032/82638032_1651479062721_1_140x140.JPG/dims/resize/Q_80,0",
      "albumName": "IM HERO",
      "artistName": "임영웅",
      "date": "2022-12-06",
      "bf_day": -10,
      "bf_week": null,
      "bf_month": null,
      "platform": "genie"
    },
    {
      "id": 1908,
      "songNumber": "96696810",
      "rank": 8,
      "title": "아버지",
      "albumArt": "https://image.genie.co.kr/Y/IMAGE/IMG_ALBUM/082/638/032/82638032_1651479062721_1_140x140.JPG/dims/resize/Q_80,0",
      "albumName": "IM HERO",
      "artistName": "임영웅",
      "date": "2022-12-06",
      "bf_day": -11,
      "bf_week": null,
      "bf_month": null,
      "platform": "genie"
    },
    {
      "id": 1909,
      "songNumber": "96696811",
      "rank": 9,
      "title": "A bientot",
      "albumArt": "https://image.genie.co.kr/Y/IMAGE/IMG_ALBUM/082/638/032/82638032_1651479062721_1_140x140.JPG/dims/resize/Q_80,0",
      "albumName": "IM HERO",
      "artistName": "임영웅",
      "date": "2022-12-06",
      "bf_day": -12,
      "bf_week": null,
      "bf_month": null,
      "platform": "genie"
    },
    {
      "id": 1910,
      "songNumber": "96696808",
      "rank": 10,
      "title": "손이 참 곱던 그대",
      "albumArt": "https://image.genie.co.kr/Y/IMAGE/IMG_ALBUM/082/638/032/82638032_1651479062721_1_140x140.JPG/dims/resize/Q_80,0",
      "albumName": "IM HERO",
      "artistName": "임영웅",
      "date": "2022-12-06",
      "bf_day": -14,
      "bf_week": null,
      "bf_month": null,
      "platform": "genie"
    },
    {
      "id": 1911,
      "songNumber": "96696814",
      "rank": 11,
      "title": "사랑해 진짜",
      "albumArt": "https://image.genie.co.kr/Y/IMAGE/IMG_ALBUM/082/638/032/82638032_1651479062721_1_140x140.JPG/dims/resize/Q_80,0",
      "albumName": "IM HERO",
      "artistName": "임영웅",
      "date": "2022-12-06",
      "bf_day": -12,
      "bf_week": null,
      "bf_month": null,
      "platform": "genie"
    },
    {
      "id": 1912,
      "songNumber": "96696815",
      "rank": 12,
      "title": "연애편지",
      "albumArt": "https://image.genie.co.kr/Y/IMAGE/IMG_ALBUM/082/638/032/82638032_1651479062721_1_140x140.JPG/dims/resize/Q_80,0",
      "albumName": "IM HERO",
      "artistName": "임영웅",
      "date": "2022-12-06",
      "bf_day": -13,
      "bf_week": null,
      "bf_month": null,
      "platform": "genie"
    },
    {
      "id": 1913,
      "songNumber": "96696817",
      "rank": 13,
      "title": "인생찬가",
      "albumArt": "https://image.genie.co.kr/Y/IMAGE/IMG_ALBUM/082/638/032/82638032_1651479062721_1_140x140.JPG/dims/resize/Q_80,0",
      "albumName": "IM HERO",
      "artistName": "임영웅",
      "date": "2022-12-06",
      "bf_day": -14,
      "bf_week": null,
      "bf_month": null,
      "platform": "genie"
    },
    {
      "id": 1914,
      "songNumber": "96696813",
      "rank": 14,
      "title": "보금자리",
      "albumArt": "https://image.genie.co.kr/Y/IMAGE/IMG_ALBUM/082/638/032/82638032_1651479062721_1_140x140.JPG/dims/resize/Q_80,0",
      "albumName": "IM HERO",
      "artistName": "임영웅",
      "date": "2022-12-06",
      "bf_day": -17,
      "bf_week": null,
      "bf_month": null,
      "platform": "genie"
    },
    {
      "id": 1915,
      "songNumber": "96424586",
      "rank": 15,
      "title": "사건의 지평선",
      "albumArt": "https://image.genie.co.kr/Y/IMAGE/IMG_ALBUM/082/614/128/82614128_1648619377015_1_140x140.JPG/dims/resize/Q_80,0",
      "albumName": "YOUNHA 6th Album Repackage 'END THEORY : Final Edition'",
      "artistName": "윤하 (YOUNHA)",
      "date": "2022-12-06",
      "bf_day": 14,
      "bf_week": null,
      "bf_month": null,
      "platform": "genie"
    },
    {
      "id": 1916,
      "songNumber": "99296683",
      "rank": 16,
      "title": "흩어지지 않게",
      "albumArt": "https://image.genie.co.kr/Y/IMAGE/IMG_ALBUM/083/251/405/83251405_1670222199633_1_140x140.JPG/dims/resize/Q_80,0",
      "albumName": "흩어지지 않게",
      "artistName": "엠씨더맥스 (M.C the MAX)",
      "date": "2022-12-06",
      "bf_day": 999,
      "bf_week": null,
      "bf_month": null,
      "platform": "genie"
    },
    {
      "id": 1917,
      "songNumber": "97582507",
      "rank": 17,
      "title": "Hype boy",
      "albumArt": "https://image.genie.co.kr/Y/IMAGE/IMG_ALBUM/082/842/800/82842800_1659340238924_1_140x140.JPG/dims/resize/Q_80,0",
      "albumName": "NewJeans 1st EP 'New Jeans'",
      "artistName": "NewJeans",
      "date": "2022-12-06",
      "bf_day": 15,
      "bf_week": null,
      "bf_month": null,
      "platform": "genie"
    },
    {
      "id": 1918,
      "songNumber": "99084793",
      "rank": 18,
      "title": "Dreamers (Music from the FIFA World Cup Qatar 2022 Official Soundtrack) (Feat. FIFA Sound)",
      "albumArt": "https://image.genie.co.kr/Y/IMAGE/IMG_ALBUM/083/196/201/83196201_1669009534084_1_140x140.JPG/dims/resize/Q_80,0",
      "albumName": "Dreamers (Music from the FIFA World Cup Qatar 2022 Official Soundtrack)",
      "artistName": "정국",
      "date": "2022-12-06",
      "bf_day": 9,
      "bf_week": null,
      "bf_month": null,
      "platform": "genie"
    },
    {
      "id": 1919,
      "songNumber": "98661235",
      "rank": 19,
      "title": "ANTIFRAGILE",
      "albumArt": "https://image.genie.co.kr/Y/IMAGE/IMG_ALBUM/083/082/184/83082184_1665969939180_1_140x140.JPG/dims/resize/Q_80,0",
      "albumName": "ANTIFRAGILE",
      "artistName": "LE SSERAFIM (르세라핌)",
      "date": "2022-12-06",
      "bf_day": 16,
      "bf_week": null,
      "bf_month": null,
      "platform": "genie"
    },
    {
      "id": 1920,
      "songNumber": "97976355",
      "rank": 20,
      "title": "After LIKE",
      "albumArt": "https://image.genie.co.kr/Y/IMAGE/IMG_ALBUM/082/912/984/82912984_1661135567760_1_140x140.JPG/dims/resize/Q_80,0",
      "albumName": "After LIKE",
      "artistName": "IVE (아이브)",
      "date": "2022-12-06",
      "bf_day": 15,
      "bf_week": null,
      "bf_month": null,
      "platform": "genie"
    },
    {
      "id": 1921,
      "songNumber": "99266256",
      "rank": 21,
      "title": "마이웨이 (MY WAY) (Prod. by R.Tee)",
      "albumArt": "https://image.genie.co.kr/Y/IMAGE/IMG_ALBUM/083/243/377/83243377_1669883362558_1_140x140.JPG/dims/resize/Q_80,0",
      "albumName": "쇼미더머니 11 Episode 1",
      "artistName": "저스디스 (JUSTHIS) & 던말릭 (DON MALIK) & 허성현 (Huh) & KHAN & 맥대디 (Mckdaddy) & Los",
      "date": "2022-12-06",
      "bf_day": 15,
      "bf_week": null,
      "bf_month": null,
      "platform": "genie"
    },
    {
      "id": 1922,
      "songNumber": "98633640",
      "rank": 22,
      "title": "Nxde",
      "albumArt": "https://image.genie.co.kr/Y/IMAGE/IMG_ALBUM/083/072/254/83072254_1665976983718_1_140x140.JPG/dims/resize/Q_80,0",
      "albumName": "I love",
      "artistName": "(여자)아이들",
      "date": "2022-12-06",
      "bf_day": 18,
      "bf_week": null,
      "bf_month": null,
      "platform": "genie"
    },
    {
      "id": 1923,
      "songNumber": "98390367",
      "rank": 23,
      "title": "그중에 그대를 만나",
      "albumArt": "https://image.genie.co.kr/Y/IMAGE/IMG_ALBUM/083/002/500/83002500_1663912084716_1_140x140.JPG/dims/resize/Q_80,0",
      "albumName": "삼남매가 용감하게 OST Part.1",
      "artistName": "김호중",
      "date": "2022-12-06",
      "bf_day": -62,
      "bf_week": null,
      "bf_month": null,
      "platform": "genie"
    },
    {
      "id": 1924,
      "songNumber": "98483245",
      "rank": 24,
      "title": "나의 목소리로",
      "albumArt": "https://image.genie.co.kr/Y/IMAGE/IMG_ALBUM/083/030/172/83030172_1664517404926_1_140x140.JPG/dims/resize/Q_80,0",
      "albumName": "나의 목소리로",
      "artistName": "김호중",
      "date": "2022-12-06",
      "bf_day": -76,
      "bf_week": null,
      "bf_month": null,
      "platform": "genie"
    },
    {
      "id": 1925,
      "songNumber": "97646911",
      "rank": 25,
      "title": "주마등",
      "albumArt": "https://image.genie.co.kr/Y/IMAGE/IMG_ALBUM/082/853/724/82853724_1658905111206_1_140x140.JPG/dims/resize/Q_80,0",
      "albumName": "PANORAMA",
      "artistName": "김호중",
      "date": "2022-12-06",
      "bf_day": 999,
      "bf_week": null,
      "bf_month": null,
      "platform": "genie"
    },
    {
      "id": 1926,
      "songNumber": "98133352",
      "rank": 26,
      "title": "새삥 (Prod. by ZICO) (Feat. 호미들)",
      "albumArt": "https://image.genie.co.kr/Y/IMAGE/IMG_ALBUM/082/941/007/82941007_1662445894361_1_140x140.JPG/dims/resize/Q_80,0",
      "albumName": "스트릿 맨 파이터(SMF) Original Vol.3 (계급미션)",
      "artistName": "지코 (ZICO)",
      "date": "2022-12-06",
      "bf_day": 19,
      "bf_week": null,
      "bf_month": null,
      "platform": "genie"
    },
    {
      "id": 1927,
      "songNumber": "98190235",
      "rank": 27,
      "title": "인생은 뷰티풀",
      "albumArt": "https://image.genie.co.kr/Y/IMAGE/IMG_ALBUM/082/952/361/82952361_1662533827668_1_140x140.JPG/dims/resize/Q_80,0",
      "albumName": "인생은 뷰티풀 : 비타돌체",
      "artistName": "김호중",
      "date": "2022-12-06",
      "bf_day": 999,
      "bf_week": null,
      "bf_month": null,
      "platform": "genie"
    },
    {
      "id": 1928,
      "songNumber": "97122560",
      "rank": 28,
      "title": "빛이 나는 사람",
      "albumArt": "https://image.genie.co.kr/Y/IMAGE/IMG_ALBUM/082/763/271/82763271_1655449446910_1_140x140.JPG/dims/resize/Q_80,0",
      "albumName": "빛이 나는 사람",
      "artistName": "김호중",
      "date": "2022-12-06",
      "bf_day": 999,
      "bf_week": null,
      "bf_month": null,
      "platform": "genie"
    },
    {
      "id": 1929,
      "songNumber": "98190234",
      "rank": 29,
      "title": "슬픈등",
      "albumArt": "https://image.genie.co.kr/Y/IMAGE/IMG_ALBUM/082/952/361/82952361_1662533827668_1_140x140.JPG/dims/resize/Q_80,0",
      "albumName": "인생은 뷰티풀 : 비타돌체",
      "artistName": "김호중",
      "date": "2022-12-06",
      "bf_day": 999,
      "bf_week": null,
      "bf_month": null,
      "platform": "genie"
    },
    {
      "id": 1930,
      "songNumber": "97646909",
      "rank": 30,
      "title": "친구",
      "albumArt": "https://image.genie.co.kr/Y/IMAGE/IMG_ALBUM/082/853/724/82853724_1658905111206_1_140x140.JPG/dims/resize/Q_80,0",
      "albumName": "PANORAMA",
      "artistName": "김호중",
      "date": "2022-12-06",
      "bf_day": 999,
      "bf_week": null,
      "bf_month": null,
      "platform": "genie"
    },
    {
      "id": 1931,
      "songNumber": "97646917",
      "rank": 31,
      "title": "약속 (約束)",
      "albumArt": "https://image.genie.co.kr/Y/IMAGE/IMG_ALBUM/082/853/724/82853724_1658905111206_1_140x140.JPG/dims/resize/Q_80,0",
      "albumName": "PANORAMA",
      "artistName": "김호중",
      "date": "2022-12-06",
      "bf_day": 999,
      "bf_week": null,
      "bf_month": null,
      "platform": "genie"
    },
    {
      "id": 1932,
      "songNumber": "98315344",
      "rank": 32,
      "title": "Monologue",
      "albumArt": "https://image.genie.co.kr/Y/IMAGE/IMG_ALBUM/082/983/095/82983095_1666323297427_1_140x140.JPG/dims/resize/Q_80,0",
      "albumName": "Monologue",
      "artistName": "테이 (Tei)",
      "date": "2022-12-06",
      "bf_day": 17,
      "bf_week": null,
      "bf_month": null,
      "platform": "genie"
    },
    {
      "id": 1933,
      "songNumber": "97646919",
      "rank": 33,
      "title": "가을꽃",
      "albumArt": "https://image.genie.co.kr/Y/IMAGE/IMG_ALBUM/082/853/724/82853724_1658905111206_1_140x140.JPG/dims/resize/Q_80,0",
      "albumName": "PANORAMA",
      "artistName": "김호중",
      "date": "2022-12-06",
      "bf_day": 999,
      "bf_week": null,
      "bf_month": null,
      "platform": "genie"
    },
    {
      "id": 1934,
      "songNumber": "97646908",
      "rank": 34,
      "title": "Il Mare Calmo Della Sera",
      "albumArt": "https://image.genie.co.kr/Y/IMAGE/IMG_ALBUM/082/853/724/82853724_1658905111206_1_140x140.JPG/dims/resize/Q_80,0",
      "albumName": "PANORAMA",
      "artistName": "김호중",
      "date": "2022-12-06",
      "bf_day": 999,
      "bf_week": null,
      "bf_month": null,
      "platform": "genie"
    },
    {
      "id": 1935,
      "songNumber": "97646913",
      "rank": 35,
      "title": "Tiritomba",
      "albumArt": "https://image.genie.co.kr/Y/IMAGE/IMG_ALBUM/082/853/724/82853724_1658905111206_1_140x140.JPG/dims/resize/Q_80,0",
      "albumName": "PANORAMA",
      "artistName": "김호중",
      "date": "2022-12-06",
      "bf_day": 999,
      "bf_week": null,
      "bf_month": null,
      "platform": "genie"
    },
    {
      "id": 1936,
      "songNumber": "96480048",
      "rank": 36,
      "title": "LOVE DIVE",
      "albumArt": "https://image.genie.co.kr/Y/IMAGE/IMG_ALBUM/082/624/363/82624363_1649123068092_1_140x140.JPG/dims/resize/Q_80,0",
      "albumName": "LOVE DIVE",
      "artistName": "IVE (아이브)",
      "date": "2022-12-06",
      "bf_day": 23,
      "bf_week": null,
      "bf_month": null,
      "platform": "genie"
    },
    {
      "id": 1937,
      "songNumber": "97582506",
      "rank": 37,
      "title": "Attention",
      "albumArt": "https://image.genie.co.kr/Y/IMAGE/IMG_ALBUM/082/842/800/82842800_1659340238924_1_140x140.JPG/dims/resize/Q_80,0",
      "albumName": "NewJeans 1st EP 'New Jeans'",
      "artistName": "NewJeans",
      "date": "2022-12-06",
      "bf_day": 26,
      "bf_week": null,
      "bf_month": null,
      "platform": "genie"
    },
    {
      "id": 1938,
      "songNumber": "90705547",
      "rank": 38,
      "title": "Dynamite",
      "albumArt": "https://image.genie.co.kr/Y/IMAGE/IMG_ALBUM/081/545/399/81545399_1600401677905_1_140x140.JPG/dims/resize/Q_80,0",
      "albumName": "Dynamite (DayTime Ver.)",
      "artistName": "방탄소년단",
      "date": "2022-12-06",
      "bf_day": -13,
      "bf_week": null,
      "bf_month": null,
      "platform": "genie"
    },
    {
      "id": 1939,
      "songNumber": "99292515",
      "rank": 39,
      "title": "잘가요",
      "albumArt": "https://image.genie.co.kr/Y/IMAGE/IMG_ALBUM/083/250/113/83250113_1669961939741_1_140x140.JPG/dims/resize/Q_80,0",
      "albumName": "잘가요",
      "artistName": "주호",
      "date": "2022-12-06",
      "bf_day": -9,
      "bf_week": null,
      "bf_month": null,
      "platform": "genie"
    },
    {
      "id": 1940,
      "songNumber": "97404330",
      "rank": 40,
      "title": "그때 그 순간 그대로 (그그그)",
      "albumArt": "https://image.genie.co.kr/Y/IMAGE/IMG_ALBUM/082/814/458/82814458_1657270030475_1_140x140.JPG/dims/resize/Q_80,0",
      "albumName": "WSG워너비 1집",
      "artistName": "WSG워너비 (가야G)",
      "date": "2022-12-06",
      "bf_day": 7,
      "bf_week": null,
      "bf_month": null,
      "platform": "genie"
    },
    {
      "id": 1941,
      "songNumber": "99266253",
      "rank": 41,
      "title": "위하여 (We Higher) (Prod. by GroovyRoom)",
      "albumArt": "https://image.genie.co.kr/Y/IMAGE/IMG_ALBUM/083/243/377/83243377_1669883362558_1_140x140.JPG/dims/resize/Q_80,0",
      "albumName": "쇼미더머니 11 Episode 1",
      "artistName": "그루비룸 (GroovyRoom) & 릴보이 (lIlBOI) & Blase (블라세) & 노윤하 & Polodared & Chillin Homie & Fleeky Bang",
      "date": "2022-12-06",
      "bf_day": 11,
      "bf_week": null,
      "bf_month": null,
      "platform": "genie"
    },
    {
      "id": 1942,
      "songNumber": "98373055",
      "rank": 42,
      "title": "Rush Hour (Feat. j-hope of BTS)",
      "albumArt": "https://image.genie.co.kr/Y/IMAGE/IMG_ALBUM/082/998/598/82998598_1663838888101_1_140x140.JPG/dims/resize/Q_80,0",
      "albumName": "Rush Hour",
      "artistName": "Crush",
      "date": "2022-12-06",
      "bf_day": 20,
      "bf_week": null,
      "bf_month": null,
      "platform": "genie"
    },
    {
      "id": 1943,
      "songNumber": "98314955",
      "rank": 43,
      "title": "Shut Down",
      "albumArt": "https://image.genie.co.kr/Y/IMAGE/IMG_ALBUM/082/912/188/82912188_1663300532914_1_140x140.JPG/dims/resize/Q_80,0",
      "albumName": "BORN PINK",
      "artistName": "BLACKPINK",
      "date": "2022-12-06",
      "bf_day": 23,
      "bf_week": null,
      "bf_month": null,
      "platform": "genie"
    },
    {
      "id": 1944,
      "songNumber": "96042335",
      "rank": 44,
      "title": "사랑인가 봐",
      "albumArt": "https://image.genie.co.kr/Y/IMAGE/IMG_ALBUM/082/540/759/82540759_1645152997958_1_140x140.JPG/dims/resize/Q_80,0",
      "albumName": "사랑인가 봐 (사내맞선 OST 스페셜 트랙)",
      "artistName": "멜로망스 (MeloMance)",
      "date": "2022-12-06",
      "bf_day": 9,
      "bf_week": null,
      "bf_month": null,
      "platform": "genie"
    },
    {
      "id": 1945,
      "songNumber": "97028103",
      "rank": 45,
      "title": "Yet To Come",
      "albumArt": "https://image.genie.co.kr/Y/IMAGE/IMG_ALBUM/082/746/162/82746162_1654826016759_1_140x140.JPG/dims/resize/Q_80,0",
      "albumName": "Proof",
      "artistName": "방탄소년단",
      "date": "2022-12-06",
      "bf_day": -30,
      "bf_week": null,
      "bf_month": null,
      "platform": "genie"
    },
    {
      "id": 1946,
      "songNumber": "97970302",
      "rank": 46,
      "title": "Pink Venom",
      "albumArt": "https://image.genie.co.kr/Y/IMAGE/IMG_ALBUM/082/912/188/82912188_1663300532914_1_140x140.JPG/dims/resize/Q_80,0",
      "albumName": "BORN PINK",
      "artistName": "BLACKPINK",
      "date": "2022-12-06",
      "bf_day": 20,
      "bf_week": null,
      "bf_month": null,
      "platform": "genie"
    },
    {
      "id": 1947,
      "songNumber": "99235358",
      "rank": 47,
      "title": "WHEN I MOVE",
      "albumArt": "https://image.genie.co.kr/Y/IMAGE/IMG_ALBUM/083/235/359/83235359_1669691783216_1_140x140.JPG/dims/resize/Q_80,0",
      "albumName": "MOVE AGAIN",
      "artistName": "카라 (KARA)",
      "date": "2022-12-06",
      "bf_day": 15,
      "bf_week": null,
      "bf_month": null,
      "platform": "genie"
    },
    {
      "id": 1948,
      "songNumber": "99291870",
      "rank": 48,
      "title": "들꽃놀이 (With 조유진)",
      "albumArt": "https://image.genie.co.kr/Y/IMAGE/IMG_ALBUM/083/249/927/83249927_1669941339337_1_140x140.JPG/dims/resize/Q_80,0",
      "albumName": "Indigo",
      "artistName": "RM",
      "date": "2022-12-06",
      "bf_day": -50,
      "bf_week": null,
      "bf_month": null,
      "platform": "genie"
    },
    {
      "id": 1949,
      "songNumber": "96276241",
      "rank": 49,
      "title": "TOMBOY",
      "albumArt": "https://image.genie.co.kr/Y/IMAGE/IMG_ALBUM/082/586/132/82586132_1647227017471_1_140x140.JPG/dims/resize/Q_80,0",
      "albumName": "I NEVER DIE",
      "artistName": "(여자)아이들",
      "date": "2022-12-06",
      "bf_day": 20,
      "bf_week": null,
      "bf_month": null,
      "platform": "genie"
    },
    {
      "id": 1950,
      "songNumber": "93352112",
      "rank": 50,
      "title": "Butter",
      "albumArt": "https://image.genie.co.kr/Y/IMAGE/IMG_ALBUM/082/055/361/82055361_1621563082144_1_140x140.JPG/dims/resize/Q_80,0",
      "albumName": "Butter",
      "artistName": "방탄소년단",
      "date": "2022-12-06",
      "bf_day": -13,
      "bf_week": null,
      "bf_month": null,
      "platform": "genie"
    },
    {
      "id": 1951,
      "songNumber": "93721048",
      "rank": 51,
      "title": "Permission to Dance",
      "albumArt": "https://image.genie.co.kr/Y/IMAGE/IMG_ALBUM/082/131/679/82131679_1625795131913_1_140x140.JPG/dims/resize/Q_80,0",
      "albumName": "Butter / Permission to Dance",
      "artistName": "방탄소년단",
      "date": "2022-12-06",
      "bf_day": -23,
      "bf_week": null,
      "bf_month": null,
      "platform": "genie"
    },
    {
      "id": 1952,
      "songNumber": "96367880",
      "rank": 52,
      "title": "내가 아니라도",
      "albumArt": "https://image.genie.co.kr/Y/IMAGE/IMG_ALBUM/082/602/752/82602752_1648117827255_1_140x140.JPG/dims/resize/Q_80,0",
      "albumName": "내가 아니라도",
      "artistName": "주호",
      "date": "2022-12-06",
      "bf_day": 14,
      "bf_week": null,
      "bf_month": null,
      "platform": "genie"
    },
    {
      "id": 1953,
      "songNumber": "86941521",
      "rank": 53,
      "title": "봄날",
      "albumArt": "https://image.genie.co.kr/Y/IMAGE/IMG_ALBUM/080/921/195/80921195_1486716752321_1_140x140.JPG/dims/resize/Q_80,0",
      "albumName": "YOU NEVER WALK ALONE",
      "artistName": "방탄소년단",
      "date": "2022-12-06",
      "bf_day": -25,
      "bf_week": null,
      "bf_month": null,
      "platform": "genie"
    },
    {
      "id": 1954,
      "songNumber": "96613134",
      "rank": 54,
      "title": "나의 X에게",
      "albumArt": "https://image.genie.co.kr/Y/IMAGE/IMG_ALBUM/082/651/870/82651870_1650613662156_1_140x140.JPG/dims/resize/Q_80,0",
      "albumName": "나의 X에게",
      "artistName": "경서",
      "date": "2022-12-06",
      "bf_day": 11,
      "bf_week": null,
      "bf_month": null,
      "platform": "genie"
    },
    {
      "id": 1955,
      "songNumber": "98796458",
      "rank": 55,
      "title": "The Astronaut",
      "albumArt": "https://image.genie.co.kr/Y/IMAGE/IMG_ALBUM/083/117/897/83117897_1666918551368_1_140x140.JPG/dims/resize/Q_80,0",
      "albumName": "The Astronaut",
      "artistName": "진",
      "date": "2022-12-06",
      "bf_day": 999,
      "bf_week": null,
      "bf_month": null,
      "platform": "genie"
    },
    {
      "id": 1956,
      "songNumber": "96951358",
      "rank": 56,
      "title": "해요 (2022)",
      "albumArt": "https://image.genie.co.kr/Y/IMAGE/IMG_ALBUM/082/727/185/82727185_1654248208229_1_140x140.JPG/dims/resize/Q_80,0",
      "albumName": "해요 (2022)",
      "artistName": "#안녕",
      "date": "2022-12-06",
      "bf_day": 16,
      "bf_week": null,
      "bf_month": null,
      "platform": "genie"
    },
    {
      "id": 1957,
      "songNumber": "98461391",
      "rank": 57,
      "title": "자격지심 (Feat. ZICO)",
      "albumArt": "https://image.genie.co.kr/Y/IMAGE/IMG_ALBUM/083/024/008/83024008_1664434674893_1_140x140.JPG/dims/resize/Q_80,0",
      "albumName": "FIVE SENSES",
      "artistName": "BE'O (비오)",
      "date": "2022-12-06",
      "bf_day": 23,
      "bf_week": null,
      "bf_month": null,
      "platform": "genie"
    },
    {
      "id": 1958,
      "songNumber": "96507978",
      "rank": 58,
      "title": "That's Hilarious",
      "albumArt": "https://image.genie.co.kr/Y/IMAGE/IMG_ALBUM/082/484/273/82484273_1665067200754_1_140x140.JPG/dims/resize/Q_80,0",
      "albumName": "CHARLIE",
      "artistName": "Charlie Puth",
      "date": "2022-12-06",
      "bf_day": 22,
      "bf_week": null,
      "bf_month": null,
      "platform": "genie"
    },
    {
      "id": 1959,
      "songNumber": "97404331",
      "rank": 59,
      "title": "보고싶었어",
      "albumArt": "https://image.genie.co.kr/Y/IMAGE/IMG_ALBUM/082/814/458/82814458_1657270030475_1_140x140.JPG/dims/resize/Q_80,0",
      "albumName": "WSG워너비 1집",
      "artistName": "WSG워너비 (4FIRE)",
      "date": "2022-12-06",
      "bf_day": 17,
      "bf_week": null,
      "bf_month": null,
      "platform": "genie"
    },
    {
      "id": 1960,
      "songNumber": "82280761",
      "rank": 60,
      "title": "너의 모든 순간",
      "albumArt": "https://image.genie.co.kr/Y/IMAGE/IMG_ALBUM/080/401/547/80401547_1392172764399_1_140x140.JPG/dims/resize/Q_80,0",
      "albumName": "별에서 온 그대 OST Part.7 (SBS 수목드라마)",
      "artistName": "성시경",
      "date": "2022-12-06",
      "bf_day": 32,
      "bf_week": null,
      "bf_month": null,
      "platform": "genie"
    },
    {
      "id": 1961,
      "songNumber": "99266255",
      "rank": 61,
      "title": "WE (Feat. 박재범) (Prod. by Slom)",
      "albumArt": "https://image.genie.co.kr/Y/IMAGE/IMG_ALBUM/083/243/377/83243377_1669883362558_1_140x140.JPG/dims/resize/Q_80,0",
      "albumName": "쇼미더머니 11 Episode 1",
      "artistName": "이영지 & 토이고 (toigo) & 제이켠 (J'Kyun) & 잠비노 (Jambino) & XINSAYNE",
      "date": "2022-12-06",
      "bf_day": 11,
      "bf_week": null,
      "bf_month": null,
      "platform": "genie"
    },
    {
      "id": 1962,
      "songNumber": "93336453",
      "rank": 62,
      "title": "다정히 내 이름을 부르면",
      "albumArt": "https://image.genie.co.kr/Y/IMAGE/IMG_ALBUM/082/051/769/82051769_1621328428038_1_140x140.JPG/dims/resize/Q_80,0",
      "albumName": "다정히 내 이름을 부르면 (경서예지 x 전건호)",
      "artistName": "경서예지 & 전건호",
      "date": "2022-12-06",
      "bf_day": 15,
      "bf_week": null,
      "bf_month": null,
      "platform": "genie"
    },
    {
      "id": 1963,
      "songNumber": "98664198",
      "rank": 63,
      "title": "떠나보낼 준비해 둘걸 그랬어",
      "albumArt": "https://image.genie.co.kr/Y/IMAGE/IMG_ALBUM/083/083/139/83083139_1666077446742_1_140x140.JPG/dims/resize/Q_80,0",
      "albumName": "떠나보낼 준비해 둘걸 그랬어",
      "artistName": "임한별",
      "date": "2022-12-06",
      "bf_day": 7,
      "bf_week": null,
      "bf_month": null,
      "platform": "genie"
    },
    {
      "id": 1964,
      "songNumber": "97313940",
      "rank": 64,
      "title": "그라데이션",
      "albumArt": "https://image.genie.co.kr/Y/IMAGE/IMG_ALBUM/082/798/875/82798875_1656663217923_1_140x140.JPG/dims/resize/Q_80,0",
      "albumName": "5.3",
      "artistName": "10CM",
      "date": "2022-12-06",
      "bf_day": 19,
      "bf_week": null,
      "bf_month": null,
      "platform": "genie"
    },
    {
      "id": 1965,
      "songNumber": "95376934",
      "rank": 65,
      "title": "취중고백",
      "albumArt": "https://image.genie.co.kr/Y/IMAGE/IMG_ALBUM/082/443/459/82443459_1639718817315_1_140x140.JPG/dims/resize/Q_80,0",
      "albumName": "취중고백",
      "artistName": "김민석 (멜로망스)",
      "date": "2022-12-06",
      "bf_day": 16,
      "bf_week": null,
      "bf_month": null,
      "platform": "genie"
    },
    {
      "id": 1966,
      "songNumber": "98390713",
      "rank": 66,
      "title": "우린 그렇게 사랑해서",
      "albumArt": "https://image.genie.co.kr/Y/IMAGE/IMG_ALBUM/083/002/608/83002608_1664167182058_1_140x140.JPG/dims/resize/Q_80,0",
      "albumName": "우린 그렇게 사랑해서",
      "artistName": "강민경 (다비치) & 잔나비 최정훈",
      "date": "2022-12-06",
      "bf_day": 22,
      "bf_week": null,
      "bf_month": null,
      "platform": "genie"
    },
    {
      "id": 1967,
      "songNumber": "98400951",
      "rank": 67,
      "title": "딱 10CM만",
      "albumArt": "https://image.genie.co.kr/Y/IMAGE/IMG_ALBUM/083/004/985/83004985_1663918763683_1_140x140.JPG/dims/resize/Q_80,0",
      "albumName": "딱 10CM만",
      "artistName": "10CM & BIG Naughty (서동현)",
      "date": "2022-12-06",
      "bf_day": 26,
      "bf_week": null,
      "bf_month": null,
      "platform": "genie"
    },
    {
      "id": 1968,
      "songNumber": "95188110",
      "rank": 68,
      "title": "ELEVEN",
      "albumArt": "https://image.genie.co.kr/Y/IMAGE/IMG_ALBUM/082/417/569/82417569_1638329272770_1_140x140.JPG/dims/resize/Q_80,0",
      "albumName": "ELEVEN",
      "artistName": "IVE (아이브)",
      "date": "2022-12-06",
      "bf_day": 29,
      "bf_week": null,
      "bf_month": null,
      "platform": "genie"
    },
    {
      "id": 1969,
      "songNumber": "82146674",
      "rank": 69,
      "title": "All I Want for Christmas Is You",
      "albumArt": "https://image.genie.co.kr/Y/IMAGE/IMG_ALBUM/080/384/589/80384589_1572569104266_1_140x140.JPG/dims/resize/Q_80,0",
      "albumName": "Merry Christmas (Deluxe Anniversary Edition)",
      "artistName": "Mariah Carey",
      "date": "2022-12-06",
      "bf_day": 32,
      "bf_week": null,
      "bf_month": null,
      "platform": "genie"
    },
    {
      "id": 1970,
      "songNumber": "99291864",
      "rank": 70,
      "title": "All Day (With Tablo)",
      "albumArt": "https://image.genie.co.kr/Y/IMAGE/IMG_ALBUM/083/249/927/83249927_1669941339337_1_140x140.JPG/dims/resize/Q_80,0",
      "albumName": "Indigo",
      "artistName": "RM",
      "date": "2022-12-06",
      "bf_day": 999,
      "bf_week": null,
      "bf_month": null,
      "platform": "genie"
    },
    {
      "id": 1971,
      "songNumber": "99291863",
      "rank": 71,
      "title": "Still Life (With Anderson .Paak)",
      "albumArt": "https://image.genie.co.kr/Y/IMAGE/IMG_ALBUM/083/249/927/83249927_1669941339337_1_140x140.JPG/dims/resize/Q_80,0",
      "albumName": "Indigo",
      "artistName": "RM",
      "date": "2022-12-06",
      "bf_day": 999,
      "bf_week": null,
      "bf_month": null,
      "platform": "genie"
    },
    {
      "id": 1972,
      "songNumber": "99291871",
      "rank": 72,
      "title": "No.2 (With 박지윤)",
      "albumArt": "https://image.genie.co.kr/Y/IMAGE/IMG_ALBUM/083/249/927/83249927_1669941339337_1_140x140.JPG/dims/resize/Q_80,0",
      "albumName": "Indigo",
      "artistName": "RM",
      "date": "2022-12-06",
      "bf_day": 999,
      "bf_week": null,
      "bf_month": null,
      "platform": "genie"
    },
    {
      "id": 1973,
      "songNumber": "99291868",
      "rank": 73,
      "title": "Lonely",
      "albumArt": "https://image.genie.co.kr/Y/IMAGE/IMG_ALBUM/083/249/927/83249927_1669941339337_1_140x140.JPG/dims/resize/Q_80,0",
      "albumName": "Indigo",
      "artistName": "RM",
      "date": "2022-12-06",
      "bf_day": 999,
      "bf_week": null,
      "bf_month": null,
      "platform": "genie"
    },
    {
      "id": 1974,
      "songNumber": "99291862",
      "rank": 74,
      "title": "Yun (With Erykah Badu)",
      "albumArt": "https://image.genie.co.kr/Y/IMAGE/IMG_ALBUM/083/249/927/83249927_1669941339337_1_140x140.JPG/dims/resize/Q_80,0",
      "albumName": "Indigo",
      "artistName": "RM",
      "date": "2022-12-06",
      "bf_day": 999,
      "bf_week": null,
      "bf_month": null,
      "platform": "genie"
    },
    {
      "id": 1975,
      "songNumber": "99291866",
      "rank": 75,
      "title": "Closer (With Paul Blanco & Mahalia)",
      "albumArt": "https://image.genie.co.kr/Y/IMAGE/IMG_ALBUM/083/249/927/83249927_1669941339337_1_140x140.JPG/dims/resize/Q_80,0",
      "albumName": "Indigo",
      "artistName": "RM",
      "date": "2022-12-06",
      "bf_day": 999,
      "bf_week": null,
      "bf_month": null,
      "platform": "genie"
    },
    {
      "id": 1976,
      "songNumber": "99291869",
      "rank": 76,
      "title": "Hectic (With Colde)",
      "albumArt": "https://image.genie.co.kr/Y/IMAGE/IMG_ALBUM/083/249/927/83249927_1669941339337_1_140x140.JPG/dims/resize/Q_80,0",
      "albumName": "Indigo",
      "artistName": "RM",
      "date": "2022-12-06",
      "bf_day": 999,
      "bf_week": null,
      "bf_month": null,
      "platform": "genie"
    },
    {
      "id": 1977,
      "songNumber": "96696680",
      "rank": 77,
      "title": "FEARLESS",
      "albumArt": "https://image.genie.co.kr/Y/IMAGE/IMG_ALBUM/082/669/125/82669125_1651458341829_1_140x140.JPG/dims/resize/Q_80,0",
      "albumName": "FEARLESS",
      "artistName": "LE SSERAFIM (르세라핌)",
      "date": "2022-12-06",
      "bf_day": 25,
      "bf_week": null,
      "bf_month": null,
      "platform": "genie"
    },
    {
      "id": 1978,
      "songNumber": "99266254",
      "rank": 78,
      "title": "아저씨",
      "albumArt": "https://image.genie.co.kr/Y/IMAGE/IMG_ALBUM/083/243/377/83243377_1669883362558_1_140x140.JPG/dims/resize/Q_80,0",
      "albumName": "쇼미더머니 11 Episode 1",
      "artistName": "릴러말즈 (Leellamarz) & 크루셜스타 (CRUCiAL STAR) & QM & 김재욱 & NSW yoon & 다민이 (DAMINI)",
      "date": "2022-12-06",
      "bf_day": 12,
      "bf_week": null,
      "bf_month": null,
      "platform": "genie"
    },
    {
      "id": 1979,
      "songNumber": "99291865",
      "rank": 79,
      "title": "건망증 (With 김사월)",
      "albumArt": "https://image.genie.co.kr/Y/IMAGE/IMG_ALBUM/083/249/927/83249927_1669941339337_1_140x140.JPG/dims/resize/Q_80,0",
      "albumName": "Indigo",
      "artistName": "RM",
      "date": "2022-12-06",
      "bf_day": 999,
      "bf_week": null,
      "bf_month": null,
      "platform": "genie"
    },
    {
      "id": 1980,
      "songNumber": "93717294",
      "rank": 80,
      "title": "Stay",
      "albumArt": "https://image.genie.co.kr/Y/IMAGE/IMG_ALBUM/082/130/513/82130513_1625722837604_1_140x140.JPG/dims/resize/Q_80,0",
      "albumName": "Stay",
      "artistName": "The Kid LAROI & Justin Bieber",
      "date": "2022-12-06",
      "bf_day": 25,
      "bf_week": null,
      "bf_month": null,
      "platform": "genie"
    },
    {
      "id": 1981,
      "songNumber": "96664100",
      "rank": 81,
      "title": "That That (Prod. & Feat. SUGA of BTS)",
      "albumArt": "https://image.genie.co.kr/Y/IMAGE/IMG_ALBUM/082/662/688/82662688_1651196114166_1_140x140.JPG/dims/resize/Q_80,0",
      "albumName": "싸다9",
      "artistName": "싸이 (Psy)",
      "date": "2022-12-06",
      "bf_day": 22,
      "bf_week": null,
      "bf_month": null,
      "platform": "genie"
    },
    {
      "id": 1982,
      "songNumber": "99291867",
      "rank": 82,
      "title": "Change pt.2",
      "albumArt": "https://image.genie.co.kr/Y/IMAGE/IMG_ALBUM/083/249/927/83249927_1669941339337_1_140x140.JPG/dims/resize/Q_80,0",
      "albumName": "Indigo",
      "artistName": "RM",
      "date": "2022-12-06",
      "bf_day": 999,
      "bf_week": null,
      "bf_month": null,
      "platform": "genie"
    },
    {
      "id": 1983,
      "songNumber": "96587489",
      "rank": 83,
      "title": "정이라고 하자 (Feat. 10CM)",
      "albumArt": "https://image.genie.co.kr/Y/IMAGE/IMG_ALBUM/082/645/633/82645633_1650352944627_1_140x140.JPG/dims/resize/Q_80,0",
      "albumName": "정이라고 하자",
      "artistName": "BIG Naughty (서동현)",
      "date": "2022-12-06",
      "bf_day": 26,
      "bf_week": null,
      "bf_month": null,
      "platform": "genie"
    },
    {
      "id": 1984,
      "songNumber": "96517321",
      "rank": 84,
      "title": "LOVE me",
      "albumArt": "https://image.genie.co.kr/Y/IMAGE/IMG_ALBUM/082/631/622/82631622_1649731154266_1_140x140.JPG/dims/resize/Q_80,0",
      "albumName": "LOVE me",
      "artistName": "BE'O (비오)",
      "date": "2022-12-06",
      "bf_day": 31,
      "bf_week": null,
      "bf_month": null,
      "platform": "genie"
    },
    {
      "id": 1985,
      "songNumber": "97680078",
      "rank": 85,
      "title": "새벽에 걸려온 너의 전화는",
      "albumArt": "https://image.genie.co.kr/Y/IMAGE/IMG_ALBUM/082/858/789/82858789_1659075929023_1_140x140.JPG/dims/resize/Q_80,0",
      "albumName": "미련을 말하는",
      "artistName": "한동근",
      "date": "2022-12-06",
      "bf_day": 4,
      "bf_week": null,
      "bf_month": null,
      "platform": "genie"
    },
    {
      "id": 1986,
      "songNumber": "98304971",
      "rank": 86,
      "title": "I Don't Think That I Like Her",
      "albumArt": "https://image.genie.co.kr/Y/IMAGE/IMG_ALBUM/082/484/273/82484273_1665067200754_1_140x140.JPG/dims/resize/Q_80,0",
      "albumName": "CHARLIE",
      "artistName": "Charlie Puth",
      "date": "2022-12-06",
      "bf_day": 32,
      "bf_week": null,
      "bf_month": null,
      "platform": "genie"
    },
    {
      "id": 1987,
      "songNumber": "99296684",
      "rank": 87,
      "title": "안녕을",
      "albumArt": "https://image.genie.co.kr/Y/IMAGE/IMG_ALBUM/083/251/405/83251405_1670222199633_1_140x140.JPG/dims/resize/Q_80,0",
      "albumName": "흩어지지 않게",
      "artistName": "엠씨더맥스 (M.C the MAX)",
      "date": "2022-12-06",
      "bf_day": 999,
      "bf_week": null,
      "bf_month": null,
      "platform": "genie"
    },
    {
      "id": 1988,
      "songNumber": "97728588",
      "rank": 88,
      "title": "Cookie",
      "albumArt": "https://image.genie.co.kr/Y/IMAGE/IMG_ALBUM/082/842/800/82842800_1659340238924_1_140x140.JPG/dims/resize/Q_80,0",
      "albumName": "NewJeans 1st EP 'New Jeans'",
      "artistName": "NewJeans",
      "date": "2022-12-06",
      "bf_day": 42,
      "bf_week": null,
      "bf_month": null,
      "platform": "genie"
    },
    {
      "id": 1989,
      "songNumber": "93300145",
      "rank": 89,
      "title": "신호등",
      "albumArt": "https://image.genie.co.kr/Y/IMAGE/IMG_ALBUM/082/045/022/82045022_1620896061233_1_140x140.JPG/dims/resize/Q_80,0",
      "albumName": "신호등",
      "artistName": "이무진",
      "date": "2022-12-06",
      "bf_day": 24,
      "bf_week": null,
      "bf_month": null,
      "platform": "genie"
    },
    {
      "id": 1990,
      "songNumber": "87840106",
      "rank": 90,
      "title": "모든 날, 모든 순간 (Every day, Every Moment)",
      "albumArt": "https://image.genie.co.kr/Y/IMAGE/IMG_ALBUM/081/044/453/81044453_1521524523818_1_140x140.JPG/dims/resize/Q_80,0",
      "albumName": "'키스 먼저 할까요?' OST Part. 3 (SBS 월화드라마)",
      "artistName": "폴킴",
      "date": "2022-12-06",
      "bf_day": 30,
      "bf_week": null,
      "bf_month": null,
      "platform": "genie"
    },
    {
      "id": 1991,
      "songNumber": "88686378",
      "rank": 91,
      "title": "주저하는 연인들을 위해",
      "albumArt": "https://image.genie.co.kr/Y/IMAGE/IMG_ALBUM/081/172/042/81172042_1552452730746_1_140x140.JPG/dims/resize/Q_80,0",
      "albumName": "전설",
      "artistName": "잔나비",
      "date": "2022-12-06",
      "bf_day": 21,
      "bf_week": null,
      "bf_month": null,
      "platform": "genie"
    },
    {
      "id": 1992,
      "songNumber": "96482850",
      "rank": 92,
      "title": "봄여름가을겨울 (Still Life)",
      "albumArt": "https://image.genie.co.kr/Y/IMAGE/IMG_ALBUM/082/624/911/82624911_1649062753955_1_140x140.JPG/dims/resize/Q_80,0",
      "albumName": "봄여름가을겨울 (Still Life)",
      "artistName": "BIGBANG (빅뱅)",
      "date": "2022-12-06",
      "bf_day": 25,
      "bf_week": null,
      "bf_month": null,
      "platform": "genie"
    },
    {
      "id": 1993,
      "songNumber": "96583743",
      "rank": 93,
      "title": "Love story",
      "albumArt": "https://image.genie.co.kr/Y/IMAGE/IMG_ALBUM/082/644/646/82644646_1650435003028_1_140x140.JPG/dims/resize/Q_80,0",
      "albumName": "Seoul",
      "artistName": "볼빨간사춘기",
      "date": "2022-12-06",
      "bf_day": 24,
      "bf_week": null,
      "bf_month": null,
      "platform": "genie"
    },
    {
      "id": 1994,
      "songNumber": "91361957",
      "rank": 94,
      "title": "밤하늘의 별을 (2020)",
      "albumArt": "https://image.genie.co.kr/Y/IMAGE/IMG_ALBUM/081/731/300/81731300_1613455604854_1_140x140.JPG/dims/resize/Q_80,0",
      "albumName": "밤하늘의 별을 (2020)",
      "artistName": "경서",
      "date": "2022-12-06",
      "bf_day": 18,
      "bf_week": null,
      "bf_month": null,
      "platform": "genie"
    },
    {
      "id": 1995,
      "songNumber": "94546037",
      "rank": 95,
      "title": "내 기쁨은 너가 벤틀리를 끄는 거야",
      "albumArt": "https://image.genie.co.kr/Y/IMAGE/IMG_ALBUM/082/324/427/82324427_1634605967340_1_140x140.JPG/dims/resize/Q_80,0",
      "albumName": "PROTOTYPE RESEARCH #0063",
      "artistName": "김승민",
      "date": "2022-12-06",
      "bf_day": 31,
      "bf_week": null,
      "bf_month": null,
      "platform": "genie"
    },
    {
      "id": 1996,
      "songNumber": "95278037",
      "rank": 96,
      "title": "참 좋은 날",
      "albumArt": "https://image.genie.co.kr/Y/IMAGE/IMG_ALBUM/082/430/226/82430226_1638955155461_1_140x140.JPG/dims/resize/Q_80,0",
      "albumName": "참 좋은 날",
      "artistName": "이찬원",
      "date": "2022-12-06",
      "bf_day": 999,
      "bf_week": null,
      "bf_month": null,
      "platform": "genie"
    },
    {
      "id": 1997,
      "songNumber": "94980637",
      "rank": 97,
      "title": "오르트구름",
      "albumArt": "https://image.genie.co.kr/Y/IMAGE/IMG_ALBUM/082/393/286/82393286_1637039913011_1_140x140.JPG/dims/resize/Q_80,0",
      "albumName": "YOUNHA 6th Album 'END THEORY'",
      "artistName": "윤하 (YOUNHA)",
      "date": "2022-12-06",
      "bf_day": 24,
      "bf_week": null,
      "bf_month": null,
      "platform": "genie"
    },
    {
      "id": 1998,
      "songNumber": "87538989",
      "rank": 98,
      "title": "Snowman",
      "albumArt": "https://image.genie.co.kr/Y/IMAGE/IMG_ALBUM/080/998/749/80998749_1643072730854_1_140x140.JPG/dims/resize/Q_80,0",
      "albumName": "Everyday Is Christmas (Snowman Deluxe Edition)",
      "artistName": "Sia",
      "date": "2022-12-06",
      "bf_day": 37,
      "bf_week": null,
      "bf_month": null,
      "platform": "genie"
    },
    {
      "id": 1999,
      "songNumber": "98133353",
      "rank": 99,
      "title": "LAW (Prod. by Czaer)",
      "albumArt": "https://image.genie.co.kr/Y/IMAGE/IMG_ALBUM/082/941/007/82941007_1662445894361_1_140x140.JPG/dims/resize/Q_80,0",
      "albumName": "스트릿 맨 파이터(SMF) Original Vol.3 (계급미션)",
      "artistName": "비비 (BIBI) & 윤미래",
      "date": "2022-12-06",
      "bf_day": 31,
      "bf_week": null,
      "bf_month": null,
      "platform": "genie"
    },
    {
      "id": 2000,
      "songNumber": "97775128",
      "rank": 100,
      "title": "FOREVER 1",
      "albumArt": "https://image.genie.co.kr/Y/IMAGE/IMG_ALBUM/082/874/768/82874768_1659669322718_1_140x140.JPG/dims/resize/Q_80,0",
      "albumName": "FOREVER 1 - The 7th Album",
      "artistName": "소녀시대 (GIRLS' GENERATION)",
      "date": "2022-12-06",
      "bf_day": 38,
      "bf_week": null,
      "bf_month": null,
      "platform": "genie"
    }
  ]
}
